odoo/addons/l10n_it_fatturapa_out_rc/README.rst
odoo/addons/l10n_it_fatturapa_out_rc/__init__.py
odoo/addons/l10n_it_fatturapa_out_rc/__manifest__.py
odoo/addons/l10n_it_fatturapa_out_rc/i18n/it.po
odoo/addons/l10n_it_fatturapa_out_rc/i18n/l10n_it_fatturapa_out_rc.pot
odoo/addons/l10n_it_fatturapa_out_rc/models/__init__.py
odoo/addons/l10n_it_fatturapa_out_rc/models/account_move.py
odoo/addons/l10n_it_fatturapa_out_rc/models/rc_type.py
odoo/addons/l10n_it_fatturapa_out_rc/readme/CONFIGURE.md
odoo/addons/l10n_it_fatturapa_out_rc/readme/CONTRIBUTORS.md
odoo/addons/l10n_it_fatturapa_out_rc/readme/DESCRIPTION.md
odoo/addons/l10n_it_fatturapa_out_rc/static/description/icon.png
odoo/addons/l10n_it_fatturapa_out_rc/static/description/index.html
odoo/addons/l10n_it_fatturapa_out_rc/tests/__init__.py
odoo/addons/l10n_it_fatturapa_out_rc/tests/test_fatturapa_xml_validation.py
odoo/addons/l10n_it_fatturapa_out_rc/tests/data/IT10538570960_00002.xml
odoo/addons/l10n_it_fatturapa_out_rc/tests/data/IT10538570960_00003.xml
odoo/addons/l10n_it_fatturapa_out_rc/tests/data/IT10538570960_00004.xml
odoo/addons/l10n_it_fatturapa_out_rc/views/invoice_it_template.xml
odoo/addons/l10n_it_fatturapa_out_rc/views/rc_type_views.xml
odoo/addons/l10n_it_fatturapa_out_rc/wizard/__init__.py
odoo/addons/l10n_it_fatturapa_out_rc/wizard/wizard_export_fatturapa.py
odoo_addon_l10n_it_fatturapa_out_rc-16.0.1.0.2.dist-info/METADATA
odoo_addon_l10n_it_fatturapa_out_rc-16.0.1.0.2.dist-info/WHEEL
odoo_addon_l10n_it_fatturapa_out_rc-16.0.1.0.2.dist-info/top_level.txt
odoo_addon_l10n_it_fatturapa_out_rc-16.0.1.0.2.dist-info/RECORD
